ed_utility/__init__.py
ed_utility/common/__init__.py
ed_utility/common/generic.py
ed_utility/common/logging.py
ed_utility/persistence/__init__.py
ed_utility/persistence/helpers.py
ed_utility/persistence/interfaces/__init__.py
ed_utility/persistence/interfaces/abc_db_client.py
ed_utility/persistence/mongo_db/__init__.py
ed_utility/persistence/mongo_db/db_client.py
ed_utility/persistence/mongo_db/unit_of_work.py
ed_utility/persistence/mongo_db/repositories/__init__.py
ed_utility/persistence/mongo_db/repositories/bill_repository.py
ed_utility/persistence/mongo_db/repositories/business_repository.py
ed_utility/persistence/mongo_db/repositories/car_repository.py
ed_utility/persistence/mongo_db/repositories/consumer_repository.py
ed_utility/persistence/mongo_db/repositories/delivery_job_repository.py
ed_utility/persistence/mongo_db/repositories/driver_repository.py
ed_utility/persistence/mongo_db/repositories/generic_repository.py
ed_utility/persistence/mongo_db/repositories/location_repository.py
ed_utility/persistence/mongo_db/repositories/order_repository.py
ed_utility/persistence/mongo_db/repositories/otp_repository.py
ed_utility/persistence/mongo_db/repositories/route_repository.py
ed_utility/persistence/mongo_db/repositories/user_repository.py
ed_utility/persistence/sqlalchemy/__init__.py
ed_utility/persistence/sqlalchemy/models/__init__.py
ed_utility/persistence/sqlalchemy/models/db_model.py
ed_utility/persistence/sqlalchemy/models/some_entity_model.py
ed_utility-0.1.0.dist-info/licenses/LICENSE
ed_utility-0.1.0.dist-info/METADATA
ed_utility-0.1.0.dist-info/WHEEL
ed_utility-0.1.0.dist-info/top_level.txt
ed_utility-0.1.0.dist-info/RECORD
